packaging_rs/__init__.py
packaging_rs/packaging_rs.cpython-39-darwin.so
packaging_rs-0.1.1.dist-info/METADATA
packaging_rs-0.1.1.dist-info/WHEEL
packaging_rs-0.1.1.dist-info/RECORD
